odoo8_addon_web_timeline-8.0.1.0.0.99.dev2-py2.7-nspkg.pth
odoo8_addon_web_timeline-8.0.1.0.0.99.dev2.dist-info/METADATA
odoo8_addon_web_timeline-8.0.1.0.0.99.dev2.dist-info/RECORD
odoo8_addon_web_timeline-8.0.1.0.0.99.dev2.dist-info/WHEEL
odoo8_addon_web_timeline-8.0.1.0.0.99.dev2.dist-info/namespace_packages.txt
odoo8_addon_web_timeline-8.0.1.0.0.99.dev2.dist-info/top_level.txt
odoo_addons/web_timeline/README.rst
odoo_addons/web_timeline/__init__.py
odoo_addons/web_timeline/__openerp__.py
odoo_addons/web_timeline/i18n/el_GR.po
odoo_addons/web_timeline/i18n/es_CO.po
odoo_addons/web_timeline/i18n/es_PY.po
odoo_addons/web_timeline/i18n/es_VE.po
odoo_addons/web_timeline/i18n/fr_CH.po
odoo_addons/web_timeline/i18n/he.po
odoo_addons/web_timeline/i18n/hr_HR.po
odoo_addons/web_timeline/i18n/lv.po
odoo_addons/web_timeline/i18n/nb_NO.po
odoo_addons/web_timeline/i18n/pt_PT.po
odoo_addons/web_timeline/i18n/sr.po
odoo_addons/web_timeline/i18n/vi.po
odoo_addons/web_timeline/i18n/web_timeline.pot
odoo_addons/web_timeline/models/__init__.py
odoo_addons/web_timeline/models/ir_view.py
odoo_addons/web_timeline/static/description/icon.png
odoo_addons/web_timeline/static/lib/vis/vis.css
odoo_addons/web_timeline/static/lib/vis/vis.js
odoo_addons/web_timeline/static/lib/vis/vis.map
odoo_addons/web_timeline/static/lib/vis/vis.min.css
odoo_addons/web_timeline/static/lib/vis/vis.min.js
odoo_addons/web_timeline/static/lib/vis/img/network/acceptDeleteIcon.png
odoo_addons/web_timeline/static/lib/vis/img/network/addNodeIcon.png
odoo_addons/web_timeline/static/lib/vis/img/network/backIcon.png
odoo_addons/web_timeline/static/lib/vis/img/network/connectIcon.png
odoo_addons/web_timeline/static/lib/vis/img/network/cross.png
odoo_addons/web_timeline/static/lib/vis/img/network/cross2.png
odoo_addons/web_timeline/static/lib/vis/img/network/deleteIcon.png
odoo_addons/web_timeline/static/lib/vis/img/network/downArrow.png
odoo_addons/web_timeline/static/lib/vis/img/network/editIcon.png
odoo_addons/web_timeline/static/lib/vis/img/network/leftArrow.png
odoo_addons/web_timeline/static/lib/vis/img/network/minus.png
odoo_addons/web_timeline/static/lib/vis/img/network/plus.png
odoo_addons/web_timeline/static/lib/vis/img/network/rightArrow.png
